uvceml/__init__.py
uvceml/uvceml.py
uvceml-1.0.dist-info/METADATA
uvceml-1.0.dist-info/WHEEL
uvceml-1.0.dist-info/top_level.txt
uvceml-1.0.dist-info/RECORD
