Metadata-Version: 2.1
Name: uvceml
Version: 1.0
Summary: List Of ML Programs
Home-page: https://github.com/Ganesh57803/uvceml
Author: Ganesh
Author-email: ganesh4study@gmail.com
License: MIT
Classifier: Programming Language :: Python :: 3
Classifier: License :: OSI Approved :: MIT License
Classifier: Operating System :: OS Independent
Requires-Python: >=3.6
Requires-Dist: numpy
Requires-Dist: pandas
Requires-Dist: scikit-learn
Requires-Dist: pgmpy
Requires-Dist: matplotlib
